relations_sqlite3.py
relations_sqlite3-0.6.7.dist-info/LICENSE.txt
relations_sqlite3-0.6.7.dist-info/METADATA
relations_sqlite3-0.6.7.dist-info/WHEEL
relations_sqlite3-0.6.7.dist-info/top_level.txt
relations_sqlite3-0.6.7.dist-info/RECORD
