Metadata-Version: 2.1
Name: relations-sqlite3
Version: 0.6.7
Summary: DB Modeling for SQLite using the sqlite3 library
Home-page: https://github.com/relations-dil/python-relations-sqlite3
Author: Gaffer Fitch
Author-email: relations@gaf3.com
Classifier: Programming Language :: Python :: 3
Classifier: License :: OSI Approved :: MIT License
License-File: LICENSE.txt
Requires-Dist: relations-dil (>=0.6.12)
Requires-Dist: relations-sqlite (>=0.6.2)
